<?xml version="1.0" encoding="UTF-8"?>
<objects serializationModel="Studio.02.03.00">
	<object class="AudioFile" id="{6e356dab-c3cd-41c0-91fe-6cc4b3714a0c}">
		<property name="assetPath">
			<value>SFXs Daniel/Hurt3.mp3</value>
		</property>
		<property name="frequencyInKHz">
			<value>44.0999985</value>
		</property>
		<property name="channelCount">
			<value>2</value>
		</property>
		<property name="length">
			<value>0.73142857142857143</value>
		</property>
		<relationship name="masterAssetFolder">
			<destination>{864ec19f-348f-47c1-990b-c4c58f33c2d4}</destination>
		</relationship>
	</object>
</objects>
